MANIFEST.in
README.md
build.py
requirements.txt
setup.py
reverse_shell/__init__.py
reverse_shell/action.py
reverse_shell/actions.py
reverse_shell/command.py
reverse_shell/data.py
reverse_shell/execution.py
reverse_shell/executor.py
reverse_shell/labels.py
reverse_shell/manager.py
reverse_shell_io.egg-info/PKG-INFO
reverse_shell_io.egg-info/SOURCES.txt
reverse_shell_io.egg-info/dependency_links.txt
reverse_shell_io.egg-info/requires.txt
reverse_shell_io.egg-info/top_level.txt