Metadata-Version: 2.1
Name: reverse-shell-io
Version: 0.0.0
Summary: A framework for designing, orchestrating and executing reverse-shell systems, with short and long term memory, dynamic execution, data delivery, multithreading live communication and more.
Home-page: https://github.com/Shahaf-F-S/backdoor
Author: Shahaf Frank-Shapir
Author-email: shahaffrs@gmail.com
License: MIT
Classifier: Intended Audience :: Developers
Classifier: License :: OSI Approved :: MIT License
Classifier: Programming Language :: Python
Classifier: Programming Language :: Python :: 3
Classifier: Programming Language :: Python :: 3.8
Classifier: Programming Language :: Python :: 3.9
Classifier: Programming Language :: Python :: 3.10
Classifier: Programming Language :: Python :: 3.11
Classifier: Operating System :: OS Independent
Requires-Dist: dacite
Requires-Dist: pyautogui
Requires-Dist: Pillow
Requires-Dist: numpy
Requires-Dist: rsa
Provides-Extra: dev
